Metadata-Version: 2.1
Name: Doc-Converter
Version: 0.0.3
Summary: This module is designed to convert all types of files into usable text str to make it easier to work with python
Author: Ibrahim
Author-email: string2025@gmail.com
License-File: license.txt
Requires-Dist: python-docx
Requires-Dist: python-pptx
Requires-Dist: pypdf2
